{
  "categories": [
    {
      "id": "clay-tools",
      "title": "Инструменты для лепки из глины",
      "subgroups": [
        {
          "id": "wire-loops",
          "title": "Проволочные петли",
          "image": "/data/images/wire-loops.jpg",
          "items": [
            {
              "id": "wl-1",
              "name": "Петля круглая малая",
              "image": "/data/images/items/wl-1.jpg",
              "images": ["/data/images/items/wl-1.jpg", "/data/images/items/wl-1-2.jpg"],
              "description": "Круглая петля малого размера для тонкой работы с глиной.",
              "features": "Нержавеющая сталь, деревянная ручка",
              "purpose": "Выборка глины в труднодоступных местах, создание углублений.",
              "type": "петля",
              "material": "сталь"
            },
            {
              "id": "wl-2",
              "name": "Петля овальная средняя",
              "image": "/data/images/items/wl-2.jpg",
              "images": ["/data/images/items/wl-2.jpg"],
              "description": "Овальная петля для средних объёмов выборки.",
              "features": "Гибкая проволока, эргономичная ручка",
              "purpose": "Формирование полостей в скульптуре.",
              "type": "петля",
              "material": "сталь"
            },
            {
              "id": "wl-3",
              "name": "Петля серповидная",
              "image": "/data/images/items/wl-3.jpg",
              "images": ["/data/images/items/wl-3.jpg"],
              "description": "Серповидная петля для грубой выборки.",
              "features": "Прочная сталь, дерево",
              "purpose": "Быстрая выборка больших объёмов глины.",
              "type": "петля",
              "material": "сталь"
            },
            {
              "id": "wl-4",
              "name": "Петля плоская",
              "image": "/data/images/items/wl-4.jpg",
              "images": ["/data/images/items/wl-4.jpg"],
              "description": "Плоская петля для выравнивания поверхностей.",
              "features": "Тонкая проволока",
              "purpose": "Срез лишней глины, выравнивание.",
              "type": "петля",
              "material": "сталь"
            },
            {
              "id": "wl-5",
              "name": "Петля треугольная",
              "image": "/data/images/items/wl-5.jpg",
              "images": ["/data/images/items/wl-5.jpg"],
              "description": "Треугольная петля для углов и граней.",
              "features": "Жёсткая проволока",
              "purpose": "Проработка углов и граней в скульптуре.",
              "type": "петля",
              "material": "сталь"
            },
            {
              "id": "wl-6",
              "name": "Петля круглая большая",
              "image": "/data/images/items/wl-6.jpg",
              "images": ["/data/images/items/wl-6.jpg"],
              "description": "Большая круглая петля для масштабных работ.",
              "features": "Усиленная конструкция",
              "purpose": "Выборка в крупных формах.",
              "type": "петля",
              "material": "сталь"
            },
            {
              "id": "wl-7",
              "name": "Петля двойная",
              "image": "/data/images/items/wl-7.jpg",
              "images": ["/data/images/items/wl-7.jpg"],
              "description": "Двойная петля для фигурной выборки.",
              "features": "Два контура",
              "purpose": "Создание сложных рельефов.",
              "type": "петля",
              "material": "сталь"
            },
            {
              "id": "wl-8",
              "name": "Петля угловая",
              "image": "/data/images/items/wl-8.jpg",
              "images": ["/data/images/items/wl-8.jpg"],
              "description": "Угловая петля 90°.",
              "features": "Жёсткий угол",
              "purpose": "Выборка в углах и пазах.",
              "type": "петля",
              "material": "сталь"
            },
            {
              "id": "wl-9",
              "name": "Петля полукруглая",
              "image": "/data/images/items/wl-9.jpg",
              "images": ["/data/images/items/wl-9.jpg"],
              "description": "Петля в форме полукруга.",
              "features": "Плавный контур",
              "purpose": "Скруглённые вырезы и канавки.",
              "type": "петля",
              "material": "сталь"
            },
            {
              "id": "wl-10",
              "name": "Петля универсальная",
              "image": "/data/images/items/wl-10.jpg",
              "images": ["/data/images/items/wl-10.jpg"],
              "description": "Универсальная петля с регулируемым контуром.",
              "features": "Сменные насадки",
              "purpose": "Широкий спектр работ по выборке.",
              "type": "петля",
              "material": "сталь"
            }
          ]
        },
        {
          "id": "wooden-stacks",
          "title": "Стеки деревянные",
          "image": "/data/images/wooden-stacks.jpg",
          "items": [
            {
              "id": "ws-1",
              "name": "Стек плоский",
              "image": "/data/images/items/ws-1.jpg",
              "images": ["/data/images/items/ws-1.jpg"],
              "description": "Деревянный стек с плоским концом.",
              "features": "Твёрдая древесина (бук)",
              "purpose": "Разглаживание и выравнивание поверхности глины.",
              "type": "стек",
              "material": "дерево"
            },
            {
              "id": "ws-2",
              "name": "Стек заострённый",
              "image": "/data/images/items/ws-2.jpg",
              "images": ["/data/images/items/ws-2.jpg"],
              "description": "Заострённый деревянный стек.",
              "features": "Бук, полировка",
              "purpose": "Детальная проработка, линии, надрезы.",
              "type": "стек",
              "material": "дерево"
            },
            {
              "id": "ws-3",
              "name": "Стек круглый",
              "image": "/data/images/items/ws-3.jpg",
              "images": ["/data/images/items/ws-3.jpg"],
              "description": "Стек с круглым наконечником.",
              "features": "Дерево",
              "purpose": "Создание углублений, оттисков.",
              "type": "стек",
              "material": "дерево"
            },
            {
              "id": "ws-4",
              "name": "Стек лопатка",
              "image": "/data/images/items/ws-4.jpg",
              "images": ["/data/images/items/ws-4.jpg"],
              "description": "Стек в форме лопатки.",
              "features": "Широкий конец",
              "purpose": "Нанесение и разравнивание глины.",
              "type": "стек",
              "material": "дерево"
            },
            {
              "id": "ws-5",
              "name": "Стек ребристый",
              "image": "/data/images/items/ws-5.jpg",
              "images": ["/data/images/items/ws-5.jpg"],
              "description": "Стек с ребристой рабочей частью.",
              "features": "Текстура для фактуры",
              "purpose": "Создание фактуры, борозд.",
              "type": "стек",
              "material": "дерево"
            },
            {
              "id": "ws-6",
              "name": "Стек двойной",
              "image": "/data/images/items/ws-6.jpg",
              "images": ["/data/images/items/ws-6.jpg"],
              "description": "Двусторонний стек с разными наконечниками.",
              "features": "Два рабочих конца",
              "purpose": "Универсальный инструмент для лепки.",
              "type": "стек",
              "material": "дерево"
            },
            {
              "id": "ws-7",
              "name": "Стек изогнутый",
              "image": "/data/images/items/ws-7.jpg",
              "images": ["/data/images/items/ws-7.jpg"],
              "description": "Изогнутый деревянный стек.",
              "features": "Удобен для вогнутых поверхностей",
              "purpose": "Работа с внутренними поверхностями.",
              "type": "стек",
              "material": "дерево"
            },
            {
              "id": "ws-8",
              "name": "Стек-нож",
              "image": "/data/images/items/ws-8.jpg",
              "images": ["/data/images/items/ws-8.jpg"],
              "description": "Деревянный стек с режущей кромкой.",
              "features": "Тупое лезвие",
              "purpose": "Резка пластов глины, подрезка.",
              "type": "стек",
              "material": "дерево"
            },
            {
              "id": "ws-9",
              "name": "Стек мини",
              "image": "/data/images/items/ws-9.jpg",
              "images": ["/data/images/items/ws-9.jpg"],
              "description": "Миниатюрный деревянный стек.",
              "features": "Маленький размер",
              "purpose": "Мелкие детали, миниатюры.",
              "type": "стек",
              "material": "дерево"
            },
            {
              "id": "ws-10",
              "name": "Стек шпатель",
              "image": "/data/images/items/ws-10.jpg",
              "images": ["/data/images/items/ws-10.jpg"],
              "description": "Шпателевидный деревянный стек.",
              "features": "Широкая плоская часть",
              "purpose": "Размазывание, выравнивание больших площадей.",
              "type": "стек",
              "material": "дерево"
            }
          ]
        }
      ]
    },
    {
      "id": "stone-tools",
      "title": "Инструменты для работы с камнем",
      "subgroups": [
        {
          "id": "scarpeli",
          "title": "Скарпели (прямые долота)",
          "image": "/data/images/chisels.jpg",
          "items": [
            {
              "id": "sc-1",
              "name": "Скарпель прямая узкая",
              "image": "/data/images/chisels.jpg",
              "images": ["/data/images/chisels.jpg"],
              "description": "Прямое долото узкой ширины для точной обработки камня.",
              "features": "Закалённая сталь, деревянная ручка",
              "purpose": "Резка прямых линий, снятие тонких слоёв камня.",
              "type": "Скарпели (прямые долота)",
              "material": "сталь"
            },
            {
              "id": "sc-2",
              "name": "Скарпель прямая широкая",
              "image": "/data/images/chisels.jpg",
              "images": ["/data/images/chisels.jpg"],
              "description": "Широкое прямое долото для грубой обтёски.",
              "features": "Толстое лезвие, прочная рукоять",
              "purpose": "Массовая сколка камня, выравнивание плоскостей.",
              "type": "Скарпели (прямые долота)",
              "material": "сталь"
            },
            {
              "id": "sc-3",
              "name": "Долото прямое зубильное",
              "image": "/data/images/chisels.jpg",
              "images": ["/data/images/chisels.jpg"],
              "description": "Прямое зубило для работы с мрамором и известняком.",
              "features": "Нержавеющая сталь",
              "purpose": "Резка по камню, создание граней.",
              "type": "Скарпели (прямые долота)",
              "material": "сталь"
            }
          ]
        },
        {
          "id": "kanavochniki",
          "title": "Канавочники",
          "image": "/data/images/chisels.jpg",
          "items": [
            {
              "id": "kv-1",
              "name": "Канавочник полукруглый малый",
              "image": "/data/images/chisels.jpg",
              "images": ["/data/images/chisels.jpg"],
              "description": "Полукруглое долото для выборки канавок малого радиуса.",
              "features": "Изогнутое лезвие, эргономичная ручка",
              "purpose": "Прорезка желобов, декоративных канавок в камне.",
              "type": "Канавочники",
              "material": "сталь"
            },
            {
              "id": "kv-2",
              "name": "Канавочник V-образный",
              "image": "/data/images/chisels.jpg",
              "images": ["/data/images/chisels.jpg"],
              "description": "Долото с V-образным профилем для острых канавок.",
              "features": "Угол 90°, закалённая сталь",
              "purpose": "Чёткие грани, надписи, орнамент.",
              "type": "Канавочники",
              "material": "сталь"
            },
            {
              "id": "kv-3",
              "name": "Канавочник широкий",
              "image": "/data/images/chisels.jpg",
              "images": ["/data/images/chisels.jpg"],
              "description": "Широкий канавочник для глубоких желобов.",
              "features": "Большой радиус, усиленная рукоять",
              "purpose": "Крупные канавки, декоративная выборка.",
              "type": "Канавочники",
              "material": "сталь"
            }
          ]
        },
        {
          "id": "rashpili",
          "title": "Рашпили скульптурные",
          "image": "/data/images/chisels.jpg",
          "items": [
            {
              "id": "rs-1",
              "name": "Рашпиль плоский скульптурный",
              "image": "/data/images/chisels.jpg",
              "images": ["/data/images/chisels.jpg"],
              "description": "Плоский рашпиль для сглаживания и формовки камня.",
              "features": "Крупная насечка, стальное полотно",
              "purpose": "Снятие неровностей, подготовка поверхности.",
              "type": "Рашпили скульптурные",
              "material": "сталь"
            },
            {
              "id": "rs-2",
              "name": "Рашпиль круглый",
              "image": "/data/images/chisels.jpg",
              "images": ["/data/images/chisels.jpg"],
              "description": "Круглый рашпиль для вогнутых поверхностей и отверстий.",
              "features": "Цилиндрическая форма, двусторонняя насечка",
              "purpose": "Обработка полостей, скруглений в скульптуре.",
              "type": "Рашпили скульптурные",
              "material": "сталь"
            },
            {
              "id": "rs-3",
              "name": "Рашпиль полукруглый",
              "image": "/data/images/chisels.jpg",
              "images": ["/data/images/chisels.jpg"],
              "description": "Полукруглый рашпиль для рельефа и переходов.",
              "features": "Средняя насечка, деревянная ручка",
              "purpose": "Детальная проработка рельефа, сглаживание.",
              "type": "Рашпили скульптурные",
              "material": "сталь"
            }
          ]
        }
      ]
    },
    {
      "id": "measuring-tools",
      "title": "Измерительные инструменты",
      "subgroups": [
        {
          "id": "cirkuli",
          "title": "Циркули и кронциркули",
          "image": "/data/images/calipers.jpg",
          "items": [
            {
              "id": "cr-1",
              "name": "Циркуль разметочный малый",
              "image": "/data/images/calipers.jpg",
              "images": ["/data/images/calipers.jpg"],
              "description": "Малый циркуль для разметки окружностей и дуг на заготовках.",
              "features": "Фиксируемый раствор, стальные ножки",
              "purpose": "Разметка кругов, перенос размеров.",
              "type": "Циркули и кронциркули",
              "material": "сталь"
            },
            {
              "id": "cr-2",
              "name": "Кронциркуль пружинный",
              "image": "/data/images/calipers.jpg",
              "images": ["/data/images/calipers.jpg"],
              "description": "Пружинный кронциркуль для измерения наружных размеров.",
              "features": "Пружинный механизм, точная шкала",
              "purpose": "Измерение диаметров, толщины деталей.",
              "type": "Циркули и кронциркули",
              "material": "сталь"
            },
            {
              "id": "cr-3",
              "name": "Циркуль с резьбовым раствором",
              "image": "/data/images/calipers.jpg",
              "images": ["/data/images/calipers.jpg"],
              "description": "Циркуль с точной настройкой раствора по резьбе.",
              "features": "Микрометрическая точность, закалённые наконечники",
              "purpose": "Точная разметка и измерение радиусов.",
              "type": "Циркули и кронциркули",
              "material": "сталь"
            }
          ]
        },
        {
          "id": "otvesy",
          "title": "Отвесы",
          "image": "/data/images/calipers.jpg",
          "items": [
            {
              "id": "ot-1",
              "name": "Отвес скульптурный 200 г",
              "image": "/data/images/calipers.jpg",
              "images": ["/data/images/calipers.jpg"],
              "description": "Отвес средней массы для проверки вертикали при установке скульптуры.",
              "features": "Стальной конус, капроновая нить",
              "purpose": "Выравнивание по вертикали, контроль установки.",
              "type": "Отвесы",
              "material": "сталь"
            },
            {
              "id": "ot-2",
              "name": "Отвес тяжёлый 500 г",
              "image": "/data/images/calipers.jpg",
              "images": ["/data/images/calipers.jpg"],
              "description": "Тяжёлый отвес для крупных работ и уличных скульптур.",
              "features": "Усиленная нить, массивный груз",
              "purpose": "Вертикаль при монтаже крупных форм.",
              "type": "Отвесы",
              "material": "сталь"
            }
          ]
        },
        {
          "id": "kallipery",
          "title": "Калиперы",
          "image": "/data/images/calipers.jpg",
          "items": [
            {
              "id": "kl-1",
              "name": "Калипер наружный 150 мм",
              "image": "/data/images/calipers.jpg",
              "images": ["/data/images/calipers.jpg"],
              "description": "Калипер для измерения наружных размеров до 150 мм.",
              "features": "Штангенциркуль тип I, нониус 0,1 мм",
              "purpose": "Точное измерение диаметров и толщин.",
              "type": "Калиперы",
              "material": "сталь"
            },
            {
              "id": "kl-2",
              "name": "Калипер внутренний",
              "image": "/data/images/calipers.jpg",
              "images": ["/data/images/calipers.jpg"],
              "description": "Калипер для измерения внутренних размеров и пазов.",
              "features": "Обратные губки, шкала 0,1 мм",
              "purpose": "Измерение отверстий, полостей, пазов.",
              "type": "Калиперы",
              "material": "сталь"
            }
          ]
        }
      ]
    },
    {
      "id": "auxiliary-tools",
      "title": "Вспомогательные инструменты",
      "subgroups": [
        {
          "id": "molotki",
          "title": "Молотки скульптурные",
          "image": "/data/images/hammers.jpg",
          "items": [
            {
              "id": "mo-1",
              "name": "Молоток скульптурный киянка деревянная",
              "image": "/data/images/hammers.jpg",
              "images": ["/data/images/hammers.jpg"],
              "description": "Деревянная киянка для ударов по скарпели и долотам.",
              "features": "Твёрдая древесина (бук), удобная рукоять",
              "purpose": "Ударное долбление камня без повреждения инструмента.",
              "type": "Молотки скульптурные",
              "material": "дерево"
            },
            {
              "id": "mo-2",
              "name": "Молоток металлический скульптурный",
              "image": "/data/images/hammers.jpg",
              "images": ["/data/images/hammers.jpg"],
              "description": "Металлический молоток для грубой сколки камня.",
              "features": "Закалённый бойок, прочная ручка",
              "purpose": "Сильные удары по зубилу, раскалывание.",
              "type": "Молотки скульптурные",
              "material": "сталь"
            }
          ]
        },
        {
          "id": "shchetki",
          "title": "Металлические щетки",
          "image": "/data/images/sponges.jpg",
          "items": [
            {
              "id": "sh-1",
              "name": "Щётка металлическая ручная",
              "image": "/data/images/sponges.jpg",
              "images": ["/data/images/sponges.jpg"],
              "description": "Ручная металлическая щётка для очистки камня и инструмента.",
              "features": "Стальная щетина, деревянная ручка",
              "purpose": "Удаление окалины, ржавчины, очистка поверхности камня.",
              "type": "Металлические щетки",
              "material": "сталь"
            },
            {
              "id": "sh-2",
              "name": "Щётка-скребок комбинированная",
              "image": "/data/images/sponges.jpg",
              "images": ["/data/images/sponges.jpg"],
              "description": "Щётка с боковым скребком для труднодоступных мест.",
              "features": "Жёсткая щетина, стальной скребок",
              "purpose": "Очистка пазов, углов, финишная обработка.",
              "type": "Металлические щетки",
              "material": "сталь"
            }
          ]
        },
        {
          "id": "klinya",
          "title": "Клинья",
          "image": "/data/images/sponges.jpg",
          "items": [
            {
              "id": "klv-1",
              "name": "Клин стальной скульптурный",
              "image": "/data/images/sponges.jpg",
              "images": ["/data/images/sponges.jpg"],
              "description": "Стальной клин для раскалывания и откола камня.",
              "features": "Закалённая сталь, тупой угол",
              "purpose": "Раскалывание блоков, откол крупных кусков.",
              "type": "Клинья",
              "material": "сталь"
            },
            {
              "id": "klv-2",
              "name": "Клинья набор из 3 шт",
              "image": "/data/images/sponges.jpg",
              "images": ["/data/images/sponges.jpg"],
              "description": "Набор клиньев разного размера для контролируемого раскалывания.",
              "features": "Три размера, сталь",
              "purpose": "Точный откол по линии, подготовка блоков.",
              "type": "Клинья",
              "material": "сталь"
            }
          ]
        }
      ]
    }
  ]
}
